{
  "main": {
    "id": "19284cc703e8b0d1",
    "type": "split",
    "children": [
      {
        "id": "292dceb89fbbfb52",
        "type": "tabs",
        "children": [
          {
            "id": "65588a3e76d9acb5",
            "type": "leaf",
            "state": {
              "type": "markdown",
              "state": {
                "file": "HackViser/CAPT (Certified Associate Penetration Tester)/4.Ağ Güvenliği ve Sızma Testi/3.Metasploit Framework Kullanımı/11.MSFvenom.md",
                "mode": "source",
                "source": false
              },
              "icon": "lucide-file",
              "title": "11.MSFvenom"
            }
          },
          {
            "id": "7eb2b9554305f187",
            "type": "leaf",
            "state": {
              "type": "markdown",
              "state": {
                "file": "CAPT (Certified Associate Penetration Tester)/CAPT (Certified Associate Penetration Tester).md",
                "mode": "source",
                "source": false
              },
              "icon": "lucide-file",
              "title": "CAPT (Certified Associate Penetration Tester)"
            }
          }
        ],
        "currentTab": 1
      }
    ],
    "direction": "vertical"
  },
  "left": {
    "id": "57cd6b3de9257217",
    "type": "split",
    "children": [
      {
        "id": "1a76d37da823c7a5",
        "type": "tabs",
        "children": [
          {
            "id": "b3303defa3022f0e",
            "type": "leaf",
            "state": {
              "type": "file-explorer",
              "state": {
                "sortOrder": "alphabetical",
                "autoReveal": false
              },
              "icon": "lucide-folder-closed",
              "title": "Dosya Gezgini"
            }
          },
          {
            "id": "7401a109f55891b2",
            "type": "leaf",
            "state": {
              "type": "search",
              "state": {
                "query": "defender",
                "matchingCase": true,
                "explainSearch": false,
                "collapseAll": false,
                "extraContext": false,
                "sortOrder": "alphabetical"
              },
              "icon": "lucide-search",
              "title": "Search"
            }
          },
          {
            "id": "4ab665b313525bdb",
            "type": "leaf",
            "state": {
              "type": "bookmarks",
              "state": {},
              "icon": "lucide-bookmark",
              "title": "Bookmarks"
            }
          }
        ]
      }
    ],
    "direction": "horizontal",
    "width": 491.5
  },
  "right": {
    "id": "6979ccb01ba2db03",
    "type": "split",
    "children": [
      {
        "id": "f716e9ab5f5f4571",
        "type": "tabs",
        "children": [
          {
            "id": "377414848ef094a9",
            "type": "leaf",
            "state": {
              "type": "backlink",
              "state": {
                "file": "Welcome.md",
                "collapseAll": false,
                "extraContext": false,
                "sortOrder": "alphabetical",
                "showSearch": false,
                "searchQuery": "",
                "backlinkCollapsed": false,
                "unlinkedCollapsed": true
              },
              "icon": "links-coming-in",
              "title": "Backlinks for Welcome"
            }
          },
          {
            "id": "69a7cf041b6bf41d",
            "type": "leaf",
            "state": {
              "type": "outgoing-link",
              "state": {
                "file": "Welcome.md",
                "linksCollapsed": false,
                "unlinkedCollapsed": true
              },
              "icon": "links-going-out",
              "title": "Outgoing links from Welcome"
            }
          },
          {
            "id": "8da082b90ddd909d",
            "type": "leaf",
            "state": {
              "type": "tag",
              "state": {
                "sortOrder": "frequency",
                "useHierarchy": true,
                "showSearch": false,
                "searchQuery": ""
              },
              "icon": "lucide-tags",
              "title": "Tags"
            }
          },
          {
            "id": "bbdbeeb1c4648f77",
            "type": "leaf",
            "state": {
              "type": "all-properties",
              "state": {
                "sortOrder": "frequency",
                "showSearch": false,
                "searchQuery": ""
              },
              "icon": "lucide-archive",
              "title": "All properties"
            }
          },
          {
            "id": "4d265fabbd14c642",
            "type": "leaf",
            "state": {
              "type": "outline",
              "state": {
                "file": "Welcome.md",
                "followCursor": false,
                "showSearch": false,
                "searchQuery": ""
              },
              "icon": "lucide-list",
              "title": "Outline of Welcome"
            }
          },
          {
            "id": "39c4faf5e2f811f8",
            "type": "leaf",
            "state": {
              "type": "empty",
              "state": {},
              "icon": "lucide-file",
              "title": "Yeni sekme"
            }
          },
          {
            "id": "07b9fbfc5b3522bf",
            "type": "leaf",
            "state": {
              "type": "empty",
              "state": {},
              "icon": "lucide-file",
              "title": "Yeni sekme"
            }
          },
          {
            "id": "b2e1add66eef2856",
            "type": "leaf",
            "state": {
              "type": "BC-matrix",
              "state": {},
              "icon": "lucide-ghost",
              "title": "BC-matrix"
            }
          },
          {
            "id": "cc6687629a7781db",
            "type": "leaf",
            "state": {
              "type": "BC-tree",
              "state": {},
              "icon": "lucide-ghost",
              "title": "BC-tree"
            }
          }
        ],
        "currentTab": 8
      }
    ],
    "direction": "horizontal",
    "width": 300,
    "collapsed": true
  },
  "left-ribbon": {
    "hiddenItems": {
      "switcher:Hızlı geçişi aç": false,
      "graph:Grafik görünümünü aç": false,
      "canvas:Yeni tuval oluşturun": false,
      "daily-notes:Bugünün Notunu Aç": false,
      "templates:Şablon ekle": false,
      "command-palette:Komut paletini aç": false,
      "bases:Yeni taban oluştur": false,
      "obsidian-git:Open Git source control": false,
      "table-editor-obsidian:Advanced Tables Toolbar": false
    }
  },
  "active": "7eb2b9554305f187",
  "lastOpenFiles": [
    "CAPT (Certified Associate Penetration Tester)/5.Web Uygulama Güvenliği/9.SQL Injection/9.SQL Injection'dan Korunma Yöntemleri.md",
    "CAPT (Certified Associate Penetration Tester)/5.Web Uygulama Güvenliği/9.SQL Injection/9.SQL Injection.md",
    "CAPT (Certified Associate Penetration Tester)/5.Web Uygulama Güvenliği/9.SQL Injection/8.Boolean Based SQL Injection.md",
    "CAPT (Certified Associate Penetration Tester)/5.Web Uygulama Güvenliği/9.SQL Injection/7.UNION Based SQL Injection.md",
    "HackViser/CAPT (Certified Associate Penetration Tester)/5.Web Uygulama Güvenliği/9.SQL Injection/Başlıksız",
    "CAPT (Certified Associate Penetration Tester)/5.Web Uygulama Güvenliği/9.SQL Injection/6.SQL Injection'a Giriş.md",
    "CAPT (Certified Associate Penetration Tester)/5.Web Uygulama Güvenliği/9.SQL Injection/5.Özel Karakterler.md",
    "CAPT (Certified Associate Penetration Tester)/5.Web Uygulama Güvenliği/9.SQL Injection/4.Mantıksal Operatörler.md",
    "CAPT (Certified Associate Penetration Tester)/5.Web Uygulama Güvenliği/9.SQL Injection/3.SQL Temelleri.md",
    "CAPT (Certified Associate Penetration Tester)/5.Web Uygulama Güvenliği/9.SQL Injection/2.Veri Tabanları.md",
    "CAPT (Certified Associate Penetration Tester)/5.Web Uygulama Güvenliği/9.SQL Injection/1.Giriş.md",
    "CAPT (Certified Associate Penetration Tester)/5.Web Uygulama Güvenliği/5.Web Uygulama Güvenliği.md",
    "CAPT (Certified Associate Penetration Tester)/5.Web Uygulama Güvenliği/9.SQL Injection",
    "CAPT (Certified Associate Penetration Tester)/5.Web Uygulama Güvenliği/8.Cross-site Scripting (XSS)/8.XSS Zafiyeti Tarama Araçları.md",
    "CAPT (Certified Associate Penetration Tester)/5.Web Uygulama Güvenliği/8.Cross-site Scripting (XSS)/8.Cross-site Scripting (XSS).md",
    "CAPT (Certified Associate Penetration Tester)/5.Web Uygulama Güvenliği/8.Cross-site Scripting (XSS)/7.Oturum Ele Geçirme Saldırısı (Session Hijacking Attack).md",
    "CAPT (Certified Associate Penetration Tester)/5.Web Uygulama Güvenliği/8.Cross-site Scripting (XSS)/6.Sık Kullanılan XSS Payload Listesi.md",
    "CAPT (Certified Associate Penetration Tester)/5.Web Uygulama Güvenliği/8.Cross-site Scripting (XSS)/5.Blind XSS (Kör XSS).md",
    "CAPT (Certified Associate Penetration Tester)/5.Web Uygulama Güvenliği/8.Cross-site Scripting (XSS)/4.DOM-based XSS (DOM Tabanlı XSS).md",
    "CAPT (Certified Associate Penetration Tester)/5.Web Uygulama Güvenliği/8.Cross-site Scripting (XSS)/3.Stored XSS (Kalıcı XSS).md",
    "CAPT (Certified Associate Penetration Tester)/5.Web Uygulama Güvenliği/8.Cross-site Scripting (XSS)/2.Reflected XSS (Kalıcı Olmayan XSS).md",
    "CAPT (Certified Associate Penetration Tester)/5.Web Uygulama Güvenliği/8.Cross-site Scripting (XSS)/1.Giriş.md",
    "CAPT (Certified Associate Penetration Tester)/5.Web Uygulama Güvenliği/8.Cross-site Scripting (XSS)",
    "CAPT (Certified Associate Penetration Tester)/6.Yetki Yükseltme Teknikleri/6.Yetki Yükseltme Teknikleri.md",
    "CAPT (Certified Associate Penetration Tester)/5.Web Uygulama Güvenliği/7.Web Uygulamalarında Brute-Force/8.Captcha Bypass Brute Force.md",
    "CAPT (Certified Associate Penetration Tester)/5.Web Uygulama Güvenliği/7.Web Uygulamalarında Brute-Force/7.Web Uygulamalarında Brute-Force.md",
    "CAPT (Certified Associate Penetration Tester)/5.Web Uygulama Güvenliği/7.Web Uygulamalarında Brute-Force/7.POST Parametre Fuzzing.md",
    "CAPT (Certified Associate Penetration Tester)/5.Web Uygulama Güvenliği/7.Web Uygulamalarında Brute-Force/6.GET Parametre Fuzzing.md",
    "CAPT (Certified Associate Penetration Tester)/5.Web Uygulama Güvenliği/7.Web Uygulamalarında Brute-Force/5.Vhost Tarama.md",
    "CAPT (Certified Associate Penetration Tester)/5.Web Uygulama Güvenliği/7.Web Uygulamalarında Brute-Force",
    "CAPT (Certified Associate Penetration Tester)/5.Web Uygulama Güvenliği/6.Subdomain Tarama",
    "CAPT (Certified Associate Penetration Tester)/5.Web Uygulama Güvenliği/5.Dizin Tarama",
    "CAPT (Certified Associate Penetration Tester)/5.Web Uygulama Güvenliği/4.Burp Suite Kullanımı",
    "CAPT (Certified Associate Penetration Tester)/5.Web Uygulama Güvenliği/3.Web Uygulamalarında Bilgi Toplama",
    "CAPT (Certified Associate Penetration Tester)/5.Web Uygulama Güvenliği/2.Modern Web Nasıl Çalışır",
    "CAPT (Certified Associate Penetration Tester)/5.Web Uygulama Güvenliği/1.Web Temelleri",
    "Pasted image 20260228222155.png",
    "Pasted image 20260228221139.png",
    "Başlıksız 1/0d336e49-6d86-44fc-8ba6-1ac4f0332a96_ExportBlock-50a6797e-5f87-40e2-9a34-8693b5f30aea/ExportBlock-50a6797e-5f87-40e2-9a34-8693b5f30aea-Part-1/image.png",
    "Pasted image 20260225191645.png"
  ]
}